pyjubjub-0.1.0.dist-info/METADATA
pyjubjub-0.1.0.dist-info/WHEEL
pyjubjub-0.1.0.dist-info/licenses/LICENSE
pyjubjub/__init__.py
pyjubjub/pyjubjub.cpython-311-x86_64-linux-gnu.so
pyjubjub-0.1.0.dist-info/RECORD
