Metadata-Version: 2.4
Name: pyjubjub
Version: 0.1.0
Classifier: Topic :: Security :: Cryptography
Classifier: Programming Language :: Rust
Classifier: Programming Language :: Python :: Implementation :: CPython
Classifier: Programming Language :: Python :: Implementation :: PyPy
License-File: LICENSE
Summary: Python interface to the Jubjub elliptic curve used in Zcash Protocol
Keywords: jubjub,zcash,elliptic,curve
Author: Duke Leto
License: GPL-3.0-or-later
Requires-Python: >=3.8
Project-URL: Homepage, https://hush.is
Project-URL: Repository, https://git.hush.is/hush/pyjubjub
Project-URL: Issues, https://git.hush.is/hush/pyjubjub/issues
